[
  {
    "name": "theme_info",
    "theme_name": "WINGROW Theme",
    "theme_version": "1.0.0",
    "theme_author": "WINGROW",
    "theme_documentation_url": "",
    "theme_support_url": ""
  },
  {
    "name": "カラー設定",
    "settings": [
      {
        "type": "color",
        "id": "color_primary",
        "label": "メインカラー（赤）",
        "default": "#c0392b"
      },
      {
        "type": "color",
        "id": "color_navy",
        "label": "ネイビーカラー",
        "default": "#1a2a4a"
      },
      {
        "type": "color",
        "id": "color_secondary",
        "label": "サブ背景色",
        "default": "#f5f0e8"
      }
    ]
  },
  {
    "name": "フォント設定",
    "settings": [
      {
        "type": "font_picker",
        "id": "type_body_font",
        "label": "本文フォント",
        "default": "sans-serif"
      },
      {
        "type": "font_picker",
        "id": "type_heading_font",
        "label": "見出しフォント",
        "default": "sans-serif"
      }
    ]
  },
  {
    "name": "SNS・ソーシャル",
    "settings": [
      {
        "type": "text",
        "id": "social_twitter_link",
        "label": "X (Twitter) URL"
      },
      {
        "type": "text",
        "id": "social_facebook_link",
        "label": "Facebook URL"
      },
      {
        "type": "text",
        "id": "social_instagram_link",
        "label": "Instagram URL"
      },
      {
        "type": "text",
        "id": "social_youtube_link",
        "label": "YouTube URL"
      },
      {
        "type": "text",
        "id": "social_tiktok_link",
        "label": "TikTok URL"
      }
    ]
  },
  {
    "name": "ファビコン",
    "settings": [
      {
        "type": "image_picker",
        "id": "favicon",
        "label": "ファビコン画像（32×32px推奨）"
      }
    ]
  },
  {
    "name": "シェア画像",
    "settings": [
      {
        "type": "image_picker",
        "id": "share_image",
        "label": "OGP共有画像（1200×628px推奨）"
      }
    ]
  }
]
